{
  "framework": "express",
  "version": "5.2.1",
  "generated": "2026-05-26T07:12:40.792Z",
  "packages_used": 18,
  "total_signatures": 30,
  "signatures": [
    {
      "type": "call",
      "member": null,
      "signature": "content-disposition(expr)",
      "args": "name || path",
      "file": ".tmp/frameworks/express-5.2.1/lib/response.js",
      "line": 464,
      "package": "content-disposition"
    },
    {
      "type": "method",
      "member": "parse",
      "signature": "content-type.parse(expr)",
      "args": "type",
      "file": ".tmp/frameworks/express-5.2.1/lib/utils.js",
      "line": 231,
      "package": "content-type"
    },
    {
      "type": "method",
      "member": "format",
      "signature": "content-type.format(expr)",
      "args": "parsed",
      "file": ".tmp/frameworks/express-5.2.1/lib/utils.js",
      "line": 237,
      "package": "content-type"
    },
    {
      "type": "call",
      "member": null,
      "signature": "cookie-signature(expr, expr)",
      "args": "val, secret",
      "file": ".tmp/frameworks/express-5.2.1/lib/response.js",
      "line": 763,
      "package": "cookie-signature"
    },
    {
      "type": "method",
      "member": "serialize",
      "signature": "cookie.serialize(expr, expr)",
      "args": "name, String(val",
      "file": ".tmp/frameworks/express-5.2.1/lib/response.js",
      "line": 779,
      "package": "cookie"
    },
    {
      "type": "call",
      "member": null,
      "signature": "debug(\"booting in %s mode\", expr)",
      "args": "'booting in %s mode', env",
      "file": ".tmp/frameworks/express-5.2.1/lib/application.js",
      "line": 107,
      "package": "debug"
    },
    {
      "type": "call",
      "member": null,
      "signature": "debug(\".use app under %s\", expr)",
      "args": "'.use app under %s', path",
      "file": ".tmp/frameworks/express-5.2.1/lib/application.js",
      "line": 225,
      "package": "debug"
    },
    {
      "type": "call",
      "member": null,
      "signature": "debug(\"set \\\"%s\\\" to %o\", expr, expr)",
      "args": "'set \"%s\" to %o', setting, val",
      "file": ".tmp/frameworks/express-5.2.1/lib/application.js",
      "line": 357,
      "package": "debug"
    },
    {
      "type": "call",
      "member": null,
      "signature": "debug(\"require \\\"%s\\\"\", expr)",
      "args": "'require \"%s\"', mod",
      "file": ".tmp/frameworks/express-5.2.1/lib/view.js",
      "line": 78,
      "package": "debug"
    },
    {
      "type": "call",
      "member": null,
      "signature": "debug(\"lookup \\\"%s\\\"\", expr)",
      "args": "'lookup \"%s\"', name",
      "file": ".tmp/frameworks/express-5.2.1/lib/view.js",
      "line": 108,
      "package": "debug"
    },
    {
      "type": "call",
      "member": null,
      "signature": "debug(\"render \\\"%s\\\"\", expr)",
      "args": "'render \"%s\"', this.path",
      "file": ".tmp/frameworks/express-5.2.1/lib/view.js",
      "line": 136,
      "package": "debug"
    },
    {
      "type": "call",
      "member": null,
      "signature": "debug(\"stat \\\"%s\\\"\", expr)",
      "args": "'stat \"%s\"', path",
      "file": ".tmp/frameworks/express-5.2.1/lib/view.js",
      "line": 198,
      "package": "debug"
    },
    {
      "type": "call",
      "member": null,
      "signature": "depd(\"Provide a url argument\")",
      "args": "'Provide a url argument'",
      "file": ".tmp/frameworks/express-5.2.1/lib/response.js",
      "line": 831,
      "package": "depd"
    },
    {
      "type": "call",
      "member": null,
      "signature": "depd(\"Url must be a string\")",
      "args": "'Url must be a string'",
      "file": ".tmp/frameworks/express-5.2.1/lib/response.js",
      "line": 835,
      "package": "depd"
    },
    {
      "type": "call",
      "member": null,
      "signature": "depd(\"Status must be a number\")",
      "args": "'Status must be a number'",
      "file": ".tmp/frameworks/express-5.2.1/lib/response.js",
      "line": 839,
      "package": "depd"
    },
    {
      "type": "call",
      "member": null,
      "signature": "encodeurl(expr)",
      "args": "url",
      "file": ".tmp/frameworks/express-5.2.1/lib/response.js",
      "line": 802,
      "package": "encodeurl"
    },
    {
      "type": "call",
      "member": null,
      "signature": "escape-html(expr)",
      "args": "address",
      "file": ".tmp/frameworks/express-5.2.1/lib/response.js",
      "line": 852,
      "package": "escape-html"
    },
    {
      "type": "call",
      "member": null,
      "signature": "etag(expr, expr)",
      "args": "buf, options",
      "file": ".tmp/frameworks/express-5.2.1/lib/utils.js",
      "line": 255,
      "package": "etag"
    },
    {
      "type": "call",
      "member": null,
      "signature": "http-errors(400, \"failed to parseInt '+nu\")",
      "args": "400, 'failed to parseInt '+num",
      "file": ".tmp/frameworks/express-5.2.1/examples/params/index.js",
      "line": 26,
      "package": "http-errors"
    },
    {
      "type": "call",
      "member": null,
      "signature": "http-errors(404, \"failed to find user\")",
      "args": "404, 'failed to find user'",
      "file": ".tmp/frameworks/express-5.2.1/examples/params/index.js",
      "line": 39,
      "package": "http-errors"
    },
    {
      "type": "call",
      "member": null,
      "signature": "merge-descriptors(expr, expr, false)",
      "args": "app, EventEmitter.prototype, false",
      "file": ".tmp/frameworks/express-5.2.1/lib/express.js",
      "line": 41,
      "package": "merge-descriptors"
    },
    {
      "type": "method",
      "member": "lookup",
      "signature": "mime-types.lookup(expr)",
      "args": "type",
      "file": ".tmp/frameworks/express-5.2.1/lib/utils.js",
      "line": 64,
      "package": "mime-types"
    },
    {
      "type": "method",
      "member": "contentType",
      "signature": "mime-types.contentType()",
      "args": "",
      "file": ".tmp/frameworks/express-5.2.1/lib/response.js",
      "line": 492,
      "package": "mime-types"
    },
    {
      "type": "method",
      "member": "contentType",
      "signature": "mime-types.contentType(expr)",
      "args": "type",
      "file": ".tmp/frameworks/express-5.2.1/lib/response.js",
      "line": 513,
      "package": "mime-types"
    },
    {
      "type": "call",
      "member": null,
      "signature": "on-finished(expr, expr)",
      "args": "res, onfinish",
      "file": ".tmp/frameworks/express-5.2.1/lib/response.js",
      "line": 998,
      "package": "on-finished"
    },
    {
      "type": "call",
      "member": null,
      "signature": "once(expr)",
      "args": "args[args.length - 1]",
      "file": ".tmp/frameworks/express-5.2.1/lib/application.js",
      "line": 602,
      "package": "once"
    },
    {
      "type": "call",
      "member": null,
      "signature": "parseurl(expr)",
      "args": "this",
      "file": ".tmp/frameworks/express-5.2.1/lib/request.js",
      "line": 225,
      "package": "parseurl"
    },
    {
      "type": "call",
      "member": null,
      "signature": "range-parser(expr, expr, expr)",
      "args": "size, range, options",
      "file": ".tmp/frameworks/express-5.2.1/lib/request.js",
      "line": 204,
      "package": "range-parser"
    },
    {
      "type": "property",
      "member": "message",
      "signature": "statuses.message",
      "args": null,
      "file": ".tmp/frameworks/express-5.2.1/lib/response.js",
      "line": 329,
      "package": "statuses"
    },
    {
      "type": "call",
      "member": null,
      "signature": "vary(expr, expr)",
      "args": "this, field",
      "file": ".tmp/frameworks/express-5.2.1/lib/response.js",
      "line": 882,
      "package": "vary"
    }
  ]
}
