{
  "generated": "2026-05-26",
  "packages": [
    {
      "pkg": "human-readable",
      "lastPublish": "2022-05-05",
      "created": "2017-11-07",
      "latest": "0.2.1",
      "ageDays": 1483
    },
    {
      "pkg": "safer-buffer",
      "lastPublish": "2022-05-16",
      "created": "2018-03-19",
      "latest": "2.1.2",
      "ageDays": 1472
    },
    {
      "pkg": "toidentifier",
      "lastPublish": "2022-05-22",
      "created": "2017-12-19",
      "latest": "1.0.1",
      "ageDays": 1466
    },
    {
      "pkg": "base64id",
      "lastPublish": "2022-06-13",
      "created": "2012-09-07",
      "latest": "2.0.0",
      "ageDays": 1444
    },
    {
      "pkg": "depd",
      "lastPublish": "2022-06-15",
      "created": "2014-06-15",
      "latest": "2.0.0",
      "ageDays": 1442
    },
    {
      "pkg": "ee-first",
      "lastPublish": "2022-06-16",
      "created": "2014-06-11",
      "latest": "1.1.1",
      "ageDays": 1441
    },
    {
      "pkg": "glob-to-regexp",
      "lastPublish": "2022-06-18",
      "created": "2013-07-16",
      "latest": "0.4.1",
      "ageDays": 1439
    },
    {
      "pkg": "is-array",
      "lastPublish": "2022-06-19",
      "created": "2014-02-26",
      "latest": "1.0.1",
      "ageDays": 1438
    },
    {
      "pkg": "is-buffer",
      "lastPublish": "2022-06-19",
      "created": "2014-10-31",
      "latest": "2.0.5",
      "ageDays": 1438
    },
    {
      "pkg": "require-directory",
      "lastPublish": "2022-06-26",
      "created": "2011-12-27",
      "latest": "2.1.1",
      "ageDays": 1431
    },
    {
      "pkg": "retry",
      "lastPublish": "2022-06-26",
      "created": "2011-05-13",
      "latest": "0.13.1",
      "ageDays": 1431
    },
    {
      "pkg": "setprototypeof",
      "lastPublish": "2022-06-26",
      "created": "2015-02-04",
      "latest": "1.2.0",
      "ageDays": 1431
    },
    {
      "pkg": "util-deprecate",
      "lastPublish": "2022-06-28",
      "created": "2014-04-30",
      "latest": "1.0.2",
      "ageDays": 1429
    },
    {
      "pkg": "normalize-path",
      "lastPublish": "2023-03-04",
      "created": "2014-06-26",
      "latest": "3.0.0",
      "ageDays": 1180
    },
    {
      "pkg": "deepmerge",
      "lastPublish": "2023-03-16",
      "created": "2012-01-31",
      "latest": "4.3.1",
      "ageDays": 1168
    },
    {
      "pkg": "has-flag",
      "lastPublish": "2023-04-17",
      "created": "2015-07-07",
      "latest": "5.0.1",
      "ageDays": 1136
    },
    {
      "pkg": "escape-string-regexp",
      "lastPublish": "2023-04-25",
      "created": "2014-06-24",
      "latest": "5.0.0",
      "ageDays": 1128
    },
    {
      "pkg": "is-number",
      "lastPublish": "2023-05-26",
      "created": "2014-09-22",
      "latest": "7.0.0",
      "ageDays": 1097
    },
    {
      "pkg": "graceful-fs",
      "lastPublish": "2023-06-09",
      "created": "2011-07-20",
      "latest": "4.2.11",
      "ageDays": 1083
    },
    {
      "pkg": "inherits",
      "lastPublish": "2023-06-09",
      "created": "2011-04-07",
      "latest": "2.0.4",
      "ageDays": 1083
    },
    {
      "pkg": "is-promise",
      "lastPublish": "2023-06-09",
      "created": "2012-12-23",
      "latest": "4.0.0",
      "ageDays": 1083
    },
    {
      "pkg": "slash",
      "lastPublish": "2023-06-09",
      "created": "2013-07-18",
      "latest": "5.1.0",
      "ageDays": 1083
    },
    {
      "pkg": "indent-string",
      "lastPublish": "2023-06-16",
      "created": "2014-06-06",
      "latest": "5.0.0",
      "ageDays": 1076
    },
    {
      "pkg": "path-key",
      "lastPublish": "2023-06-17",
      "created": "2015-12-28",
      "latest": "4.0.0",
      "ageDays": 1075
    },
    {
      "pkg": "pify",
      "lastPublish": "2023-06-17",
      "created": "2015-08-29",
      "latest": "6.1.0",
      "ageDays": 1075
    },
    {
      "pkg": "concat-map",
      "lastPublish": "2023-06-22",
      "created": "2012-06-08",
      "latest": "0.0.2",
      "ageDays": 1070
    },
    {
      "pkg": "fast-deep-equal",
      "lastPublish": "2023-06-22",
      "created": "2017-06-15",
      "latest": "3.1.3",
      "ageDays": 1070
    },
    {
      "pkg": "fast-json-stable-stringify",
      "lastPublish": "2023-06-22",
      "created": "2017-10-24",
      "latest": "2.1.0",
      "ageDays": 1070
    },
    {
      "pkg": "imurmurhash",
      "lastPublish": "2023-06-22",
      "created": "2013-07-31",
      "latest": "0.1.4",
      "ageDays": 1070
    },
    {
      "pkg": "is-glob",
      "lastPublish": "2023-06-22",
      "created": "2014-12-18",
      "latest": "4.0.3",
      "ageDays": 1070
    },
    {
      "pkg": "is-path-inside",
      "lastPublish": "2023-06-22",
      "created": "2014-06-20",
      "latest": "4.0.0",
      "ageDays": 1070
    },
    {
      "pkg": "resolve-from",
      "lastPublish": "2023-06-22",
      "created": "2014-07-20",
      "latest": "5.0.0",
      "ageDays": 1070
    },
    {
      "pkg": "wrappy",
      "lastPublish": "2023-06-22",
      "created": "2014-09-18",
      "latest": "0.0.0",
      "ageDays": 1070
    },
    {
      "pkg": "kleur",
      "lastPublish": "2023-07-09",
      "created": "2018-07-08",
      "latest": "4.1.5",
      "ageDays": 1053
    },
    {
      "pkg": "safe-buffer",
      "lastPublish": "2023-07-10",
      "created": "2016-01-13",
      "latest": "5.2.1",
      "ageDays": 1052
    },
    {
      "pkg": "triple-beam",
      "lastPublish": "2023-07-10",
      "created": "2017-09-29",
      "latest": "1.4.1",
      "ageDays": 1052
    },
    {
      "pkg": "y18n",
      "lastPublish": "2023-07-10",
      "created": "2015-07-27",
      "latest": "5.0.8",
      "ageDays": 1052
    },
    {
      "pkg": "bytes",
      "lastPublish": "2023-07-12",
      "created": "2012-06-11",
      "latest": "3.1.2",
      "ageDays": 1050
    },
    {
      "pkg": "events",
      "lastPublish": "2023-07-12",
      "created": "2011-04-22",
      "latest": "3.3.0",
      "ageDays": 1050
    },
    {
      "pkg": "is-plain-object",
      "lastPublish": "2023-07-12",
      "created": "2014-09-21",
      "latest": "5.0.0",
      "ageDays": 1050
    },
    {
      "pkg": "path-is-absolute",
      "lastPublish": "2023-07-21",
      "created": "2015-02-17",
      "latest": "2.0.0",
      "ageDays": 1041
    },
    {
      "pkg": "memoize-one",
      "lastPublish": "2023-07-22",
      "created": "2017-02-06",
      "latest": "6.0.0",
      "ageDays": 1040
    },
    {
      "pkg": "signal-exit",
      "lastPublish": "2023-07-29",
      "created": "2015-05-16",
      "latest": "4.1.0",
      "ageDays": 1033
    },
    {
      "pkg": "get-caller-file",
      "lastPublish": "2023-09-10",
      "created": "2015-12-30",
      "latest": "2.0.5",
      "ageDays": 990
    },
    {
      "pkg": "aggregate-error",
      "lastPublish": "2023-09-14",
      "created": "2016-09-13",
      "latest": "5.0.0",
      "ageDays": 986
    },
    {
      "pkg": "function-bind",
      "lastPublish": "2023-10-12",
      "created": "2013-06-16",
      "latest": "1.1.2",
      "ageDays": 958
    },
    {
      "pkg": "mimic-fn",
      "lastPublish": "2023-11-05",
      "created": "2016-10-19",
      "latest": "5.0.0",
      "ageDays": 934
    },
    {
      "pkg": "mem",
      "lastPublish": "2023-11-14",
      "created": "2013-01-22",
      "latest": "10.0.0",
      "ageDays": 925
    },
    {
      "pkg": "escape-html",
      "lastPublish": "2023-11-16",
      "created": "2012-08-20",
      "latest": "1.0.3",
      "ageDays": 923
    },
    {
      "pkg": "merge-descriptors",
      "lastPublish": "2023-11-17",
      "created": "2013-10-29",
      "latest": "2.0.0",
      "ageDays": 922
    },
    {
      "pkg": "es-errors",
      "lastPublish": "2024-02-05",
      "created": "2024-02-03",
      "latest": "1.3.0",
      "ageDays": 842
    },
    {
      "pkg": "define-data-property",
      "lastPublish": "2024-02-13",
      "created": "2023-09-12",
      "latest": "1.1.4",
      "ageDays": 834
    },
    {
      "pkg": "is-stream",
      "lastPublish": "2024-02-19",
      "created": "2015-01-18",
      "latest": "4.0.1",
      "ageDays": 828
    },
    {
      "pkg": "set-function-length",
      "lastPublish": "2024-03-09",
      "created": "2023-10-13",
      "latest": "1.2.2",
      "ageDays": 809
    },
    {
      "pkg": "get-stream",
      "lastPublish": "2024-03-16",
      "created": "2015-10-14",
      "latest": "9.0.1",
      "ageDays": 802
    },
    {
      "pkg": "yallist",
      "lastPublish": "2024-04-09",
      "created": "2015-12-18",
      "latest": "5.0.0",
      "ageDays": 778
    },
    {
      "pkg": "deep-equal",
      "lastPublish": "2024-05-06",
      "created": "2012-02-11",
      "latest": "2.2.3",
      "ageDays": 751
    },
    {
      "pkg": "fill-range",
      "lastPublish": "2024-05-21",
      "created": "2014-11-25",
      "latest": "7.1.1",
      "ageDays": 736
    },
    {
      "pkg": "inflight",
      "lastPublish": "2024-05-23",
      "created": "2014-05-05",
      "latest": "1.0.6",
      "ageDays": 734
    },
    {
      "pkg": "filter-obj",
      "lastPublish": "2024-05-27",
      "created": "2015-08-10",
      "latest": "6.1.0",
      "ageDays": 730
    },
    {
      "pkg": "encodeurl",
      "lastPublish": "2024-05-30",
      "created": "2016-06-08",
      "latest": "2.0.0",
      "ageDays": 727
    },
    {
      "pkg": "callsites",
      "lastPublish": "2024-06-29",
      "created": "2014-04-19",
      "latest": "4.2.0",
      "ageDays": 697
    },
    {
      "pkg": "type-detect",
      "lastPublish": "2024-07-25",
      "created": "2013-08-14",
      "latest": "4.1.0",
      "ageDays": 671
    },
    {
      "pkg": "path-type",
      "lastPublish": "2024-07-26",
      "created": "2015-09-04",
      "latest": "6.0.0",
      "ageDays": 670
    },
    {
      "pkg": "escalade",
      "lastPublish": "2024-08-29",
      "created": "2020-06-19",
      "latest": "3.2.0",
      "ageDays": 636
    },
    {
      "pkg": "braces",
      "lastPublish": "2024-09-18",
      "created": "2014-10-20",
      "latest": "3.0.3",
      "ageDays": 616
    },
    {
      "pkg": "micromatch",
      "lastPublish": "2024-09-18",
      "created": "2014-11-25",
      "latest": "4.0.8",
      "ageDays": 616
    },
    {
      "pkg": "picocolors",
      "lastPublish": "2024-10-16",
      "created": "2021-09-27",
      "latest": "1.1.1",
      "ageDays": 588
    },
    {
      "pkg": "path-exists",
      "lastPublish": "2024-10-22",
      "created": "2015-05-02",
      "latest": "5.0.0",
      "ageDays": 582
    },
    {
      "pkg": "merge-stream",
      "lastPublish": "2024-10-25",
      "created": "2013-06-10",
      "latest": "2.0.0",
      "ageDays": 579
    },
    {
      "pkg": "cookie-signature",
      "lastPublish": "2024-10-29",
      "created": "2012-10-15",
      "latest": "1.2.2",
      "ageDays": 575
    },
    {
      "pkg": "fast-levenshtein",
      "lastPublish": "2024-11-04",
      "created": "2013-04-18",
      "latest": "3.0.0",
      "ageDays": 569
    },
    {
      "pkg": "cross-spawn",
      "lastPublish": "2024-11-18",
      "created": "2014-06-30",
      "latest": "6.0.6",
      "ageDays": 555
    },
    {
      "pkg": "has-symbols",
      "lastPublish": "2024-12-02",
      "created": "2016-09-19",
      "latest": "1.1.0",
      "ageDays": 541
    },
    {
      "pkg": "gopd",
      "lastPublish": "2024-12-04",
      "created": "2022-11-02",
      "latest": "1.2.0",
      "ageDays": 539
    },
    {
      "pkg": "es-define-property",
      "lastPublish": "2024-12-06",
      "created": "2024-02-13",
      "latest": "1.0.1",
      "ageDays": 537
    },
    {
      "pkg": "has-proto",
      "lastPublish": "2024-12-06",
      "created": "2022-12-13",
      "latest": "1.2.0",
      "ageDays": 537
    },
    {
      "pkg": "side-channel",
      "lastPublish": "2024-12-11",
      "created": "2019-12-02",
      "latest": "1.1.0",
      "ageDays": 532
    },
    {
      "pkg": "classnames",
      "lastPublish": "2024-12-13",
      "created": "2014-11-05",
      "latest": "2.5.1",
      "ageDays": 530
    },
    {
      "pkg": "object-inspect",
      "lastPublish": "2025-02-05",
      "created": "2013-07-26",
      "latest": "1.13.4",
      "ageDays": 476
    },
    {
      "pkg": "object-assign",
      "lastPublish": "2025-02-16",
      "created": "2014-02-02",
      "latest": "4.1.1",
      "ageDays": 465
    },
    {
      "pkg": "cliui",
      "lastPublish": "2025-03-17",
      "created": "2015-04-20",
      "latest": "9.0.1",
      "ageDays": 436
    },
    {
      "pkg": "etag",
      "lastPublish": "2025-05-14",
      "created": "2014-05-18",
      "latest": "1.8.1",
      "ageDays": 378
    },
    {
      "pkg": "forwarded",
      "lastPublish": "2025-05-14",
      "created": "2014-08-19",
      "latest": "0.2.0",
      "ageDays": 378
    },
    {
      "pkg": "fresh",
      "lastPublish": "2025-05-14",
      "created": "2012-06-10",
      "latest": "2.0.0",
      "ageDays": 378
    },
    {
      "pkg": "media-typer",
      "lastPublish": "2025-05-14",
      "created": "2014-06-13",
      "latest": "1.1.0",
      "ageDays": 378
    },
    {
      "pkg": "negotiator",
      "lastPublish": "2025-05-14",
      "created": "2012-01-26",
      "latest": "0.6.4",
      "ageDays": 378
    },
    {
      "pkg": "on-finished",
      "lastPublish": "2025-05-14",
      "created": "2014-08-16",
      "latest": "2.4.1",
      "ageDays": 378
    },
    {
      "pkg": "parseurl",
      "lastPublish": "2025-05-14",
      "created": "2014-03-08",
      "latest": "1.3.3",
      "ageDays": 378
    },
    {
      "pkg": "range-parser",
      "lastPublish": "2025-05-14",
      "created": "2012-06-11",
      "latest": "1.2.1",
      "ageDays": 378
    },
    {
      "pkg": "yargs-parser",
      "lastPublish": "2025-05-26",
      "created": "2016-01-23",
      "latest": "22.0.0",
      "ageDays": 366
    },
    {
      "pkg": "pkg-dir",
      "lastPublish": "2025-06-05",
      "created": "2015-09-01",
      "latest": "9.0.0",
      "ageDays": 356
    },
    {
      "pkg": "statuses",
      "lastPublish": "2025-06-06",
      "created": "2014-03-13",
      "latest": "2.0.2",
      "ageDays": 355
    },
    {
      "pkg": "clsx",
      "lastPublish": "2025-06-27",
      "created": "2018-12-24",
      "latest": "2.1.1",
      "ageDays": 334
    },
    {
      "pkg": "decamelize",
      "lastPublish": "2025-08-19",
      "created": "2015-01-24",
      "latest": "6.0.1",
      "ageDays": 281
    },
    {
      "pkg": "sort-keys",
      "lastPublish": "2025-08-24",
      "created": "2014-06-28",
      "latest": "6.0.0",
      "ageDays": 276
    },
    {
      "pkg": "is-fullwidth-code-point",
      "lastPublish": "2025-08-31",
      "created": "2015-07-16",
      "latest": "5.1.0",
      "ageDays": 269
    },
    {
      "pkg": "ansi-regex",
      "lastPublish": "2025-09-08",
      "created": "2014-06-03",
      "latest": "6.2.2",
      "ageDays": 261
    },
    {
      "pkg": "ansi-styles",
      "lastPublish": "2025-09-08",
      "created": "2013-07-31",
      "latest": "6.2.3",
      "ageDays": 261
    },
    {
      "pkg": "ms",
      "lastPublish": "2025-09-08",
      "created": "2011-12-21",
      "latest": "4.0.0-nightly.202508271359",
      "ageDays": 261
    },
    {
      "pkg": "supports-color",
      "lastPublish": "2025-09-08",
      "created": "2014-06-14",
      "latest": "10.2.2",
      "ageDays": 261
    },
    {
      "pkg": "debug",
      "lastPublish": "2025-09-13",
      "created": "2011-11-29",
      "latest": "4.4.3",
      "ageDays": 256
    },
    {
      "pkg": "locate-path",
      "lastPublish": "2025-09-15",
      "created": "2016-11-20",
      "latest": "8.0.0",
      "ageDays": 254
    },
    {
      "pkg": "parent-module",
      "lastPublish": "2025-09-15",
      "created": "2016-01-22",
      "latest": "3.2.0",
      "ageDays": 254
    },
    {
      "pkg": "find-up",
      "lastPublish": "2025-09-16",
      "created": "2015-09-01",
      "latest": "8.0.0",
      "ageDays": 253
    },
    {
      "pkg": "map-obj",
      "lastPublish": "2025-09-21",
      "created": "2014-10-12",
      "latest": "6.0.0",
      "ageDays": 248
    },
    {
      "pkg": "cross-env",
      "lastPublish": "2025-09-29",
      "created": "2015-10-01",
      "latest": "10.1.0",
      "ageDays": 240
    },
    {
      "pkg": "get-intrinsic",
      "lastPublish": "2025-09-30",
      "created": "2020-10-30",
      "latest": "1.3.1",
      "ageDays": 239
    },
    {
      "pkg": "strip-indent",
      "lastPublish": "2025-10-12",
      "created": "2014-03-29",
      "latest": "4.1.1",
      "ageDays": 227
    },
    {
      "pkg": "moment",
      "lastPublish": "2025-10-14",
      "created": "2011-10-17",
      "latest": "2.30.1",
      "ageDays": 225
    },
    {
      "pkg": "chalk",
      "lastPublish": "2025-10-29",
      "created": "2013-08-03",
      "latest": "5.6.2",
      "ageDays": 210
    },
    {
      "pkg": "delay",
      "lastPublish": "2025-10-31",
      "created": "2012-07-19",
      "latest": "7.0.0",
      "ageDays": 208
    },
    {
      "pkg": "clean-stack",
      "lastPublish": "2025-11-04",
      "created": "2016-07-07",
      "latest": "6.0.0",
      "ageDays": 204
    },
    {
      "pkg": "camelcase",
      "lastPublish": "2025-11-10",
      "created": "2013-10-30",
      "latest": "9.0.0",
      "ageDays": 198
    },
    {
      "pkg": "p-map",
      "lastPublish": "2025-11-11",
      "created": "2016-10-21",
      "latest": "7.0.4",
      "ageDays": 197
    },
    {
      "pkg": "color-name",
      "lastPublish": "2025-11-12",
      "created": "2014-11-23",
      "latest": "2.1.0",
      "ageDays": 196
    },
    {
      "pkg": "color-convert",
      "lastPublish": "2025-11-14",
      "created": "2011-06-10",
      "latest": "3.1.3",
      "ageDays": 194
    },
    {
      "pkg": "http-errors",
      "lastPublish": "2025-11-20",
      "created": "2012-11-18",
      "latest": "2.0.1",
      "ageDays": 188
    },
    {
      "pkg": "mime-types",
      "lastPublish": "2025-11-20",
      "created": "2014-05-02",
      "latest": "3.0.2",
      "ageDays": 188
    },
    {
      "pkg": "cookie",
      "lastPublish": "2025-11-26",
      "created": "2012-05-28",
      "latest": "1.1.1",
      "ageDays": 182
    },
    {
      "pkg": "execa",
      "lastPublish": "2025-11-29",
      "created": "2015-12-05",
      "latest": "9.6.1",
      "ageDays": 179
    },
    {
      "pkg": "eventemitter3",
      "lastPublish": "2026-01-19",
      "created": "2013-09-25",
      "latest": "5.0.4",
      "ageDays": 128
    },
    {
      "pkg": "cors",
      "lastPublish": "2026-01-22",
      "created": "2013-01-31",
      "latest": "2.8.6",
      "ageDays": 125
    },
    {
      "pkg": "onetime",
      "lastPublish": "2026-02-02",
      "created": "2013-12-13",
      "latest": "8.0.0",
      "ageDays": 114
    },
    {
      "pkg": "tempy",
      "lastPublish": "2026-02-02",
      "created": "2017-03-28",
      "latest": "3.2.0",
      "ageDays": 114
    },
    {
      "pkg": "destroy",
      "lastPublish": "2026-02-03",
      "created": "2013-10-03",
      "latest": "1.2.0",
      "ageDays": 113
    },
    {
      "pkg": "p-limit",
      "lastPublish": "2026-02-03",
      "created": "2016-10-21",
      "latest": "7.3.0",
      "ageDays": 113
    },
    {
      "pkg": "p-locate",
      "lastPublish": "2026-02-03",
      "created": "2016-11-20",
      "latest": "7.0.0",
      "ageDays": 113
    },
    {
      "pkg": "unpipe",
      "lastPublish": "2026-02-03",
      "created": "2015-06-14",
      "latest": "1.0.0",
      "ageDays": 113
    },
    {
      "pkg": "glob",
      "lastPublish": "2026-02-19",
      "created": "2011-01-02",
      "latest": "13.0.6",
      "ageDays": 97
    },
    {
      "pkg": "minipass",
      "lastPublish": "2026-02-19",
      "created": "2017-03-14",
      "latest": "7.1.3",
      "ageDays": 97
    },
    {
      "pkg": "wrap-ansi",
      "lastPublish": "2026-02-20",
      "created": "2015-08-19",
      "latest": "10.0.0",
      "ageDays": 96
    },
    {
      "pkg": "balanced-match",
      "lastPublish": "2026-02-22",
      "created": "2013-10-13",
      "latest": "4.0.4",
      "ageDays": 94
    },
    {
      "pkg": "import-fresh",
      "lastPublish": "2026-02-25",
      "created": "2017-05-21",
      "latest": "4.0.0",
      "ageDays": 91
    },
    {
      "pkg": "strip-ansi",
      "lastPublish": "2026-02-26",
      "created": "2013-12-07",
      "latest": "7.2.0",
      "ageDays": 90
    },
    {
      "pkg": "once",
      "lastPublish": "2026-03-01",
      "created": "2012-08-14",
      "latest": "1.4.0",
      "ageDays": 87
    },
    {
      "pkg": "picomatch",
      "lastPublish": "2026-03-24",
      "created": "2018-11-05",
      "latest": "4.0.4",
      "ageDays": 64
    },
    {
      "pkg": "p-retry",
      "lastPublish": "2026-03-26",
      "created": "2016-10-21",
      "latest": "8.0.0",
      "ageDays": 62
    },
    {
      "pkg": "globby",
      "lastPublish": "2026-03-27",
      "created": "2014-06-21",
      "latest": "16.2.0",
      "ageDays": 61
    },
    {
      "pkg": "minimatch",
      "lastPublish": "2026-03-30",
      "created": "2011-07-16",
      "latest": "10.2.5",
      "ageDays": 58
    },
    {
      "pkg": "lodash-es",
      "lastPublish": "2026-04-01",
      "created": "2015-01-26",
      "latest": "4.18.1",
      "ageDays": 56
    },
    {
      "pkg": "path-to-regexp",
      "lastPublish": "2026-04-01",
      "created": "2012-08-01",
      "latest": "8.4.2",
      "ageDays": 56
    },
    {
      "pkg": "rimraf",
      "lastPublish": "2026-04-03",
      "created": "2011-02-08",
      "latest": "6.1.3",
      "ageDays": 54
    },
    {
      "pkg": "call-bind",
      "lastPublish": "2026-04-09",
      "created": "2020-10-30",
      "latest": "1.0.9",
      "ageDays": 48
    },
    {
      "pkg": "dotenv-expand",
      "lastPublish": "2026-04-17",
      "created": "2016-01-21",
      "latest": "13.0.0",
      "ageDays": 40
    },
    {
      "pkg": "hasown",
      "lastPublish": "2026-04-17",
      "created": "2014-09-03",
      "latest": "2.0.3",
      "ageDays": 40
    },
    {
      "pkg": "type-fest",
      "lastPublish": "2026-04-17",
      "created": "2019-03-13",
      "latest": "5.6.0",
      "ageDays": 40
    },
    {
      "pkg": "dotenv",
      "lastPublish": "2026-04-24",
      "created": "2013-07-05",
      "latest": "17.4.2",
      "ageDays": 33
    },
    {
      "pkg": "emoji-regex",
      "lastPublish": "2026-04-24",
      "created": "2014-09-28",
      "latest": "10.6.0",
      "ageDays": 33
    },
    {
      "pkg": "mkdirp",
      "lastPublish": "2026-04-24",
      "created": "2011-01-06",
      "latest": "3.0.1",
      "ageDays": 33
    },
    {
      "pkg": "vary",
      "lastPublish": "2026-04-24",
      "created": "2014-06-04",
      "latest": "1.1.2",
      "ageDays": 33
    },
    {
      "pkg": "string-width",
      "lastPublish": "2026-04-27",
      "created": "2015-07-16",
      "latest": "8.2.1",
      "ageDays": 30
    },
    {
      "pkg": "nanoid",
      "lastPublish": "2026-04-30",
      "created": "2017-08-06",
      "latest": "5.1.11",
      "ageDays": 27
    },
    {
      "pkg": "ipaddr.js",
      "lastPublish": "2026-05-03",
      "created": "2011-07-28",
      "latest": "2.4.0",
      "ageDays": 24
    },
    {
      "pkg": "uuid",
      "lastPublish": "2026-05-04",
      "created": "2011-03-31",
      "latest": "13.0.2",
      "ageDays": 23
    },
    {
      "pkg": "which",
      "lastPublish": "2026-05-08",
      "created": "2011-08-07",
      "latest": "7.0.0",
      "ageDays": 19
    },
    {
      "pkg": "content-disposition",
      "lastPublish": "2026-05-11",
      "created": "2014-09-19",
      "latest": "2.0.0",
      "ageDays": 16
    },
    {
      "pkg": "content-type",
      "lastPublish": "2026-05-11",
      "created": "2013-10-08",
      "latest": "2.0.0",
      "ageDays": 16
    },
    {
      "pkg": "axios",
      "lastPublish": "2026-05-13",
      "created": "2014-08-29",
      "latest": "1.16.1",
      "ageDays": 14
    },
    {
      "pkg": "p-queue",
      "lastPublish": "2026-05-16",
      "created": "2016-10-28",
      "latest": "9.3.0",
      "ageDays": 11
    },
    {
      "pkg": "qs",
      "lastPublish": "2026-05-16",
      "created": "2011-02-04",
      "latest": "6.15.2",
      "ageDays": 11
    },
    {
      "pkg": "lru-cache",
      "lastPublish": "2026-05-19",
      "created": "2011-07-16",
      "latest": "11.5.0",
      "ageDays": 8
    },
    {
      "pkg": "semver",
      "lastPublish": "2026-05-21",
      "created": "2011-02-12",
      "latest": "7.8.1",
      "ageDays": 6
    },
    {
      "pkg": "lodash",
      "lastPublish": "2026-05-26",
      "created": "2012-04-23",
      "latest": "4.18.1",
      "ageDays": 1
    },
    {
      "pkg": "slash-trailing",
      "lastPublish": "not-found",
      "created": "not-found",
      "latest": "n/a",
      "ageDays": -1
    }
  ]
}
